collabme/__init__.py
collabme/connector.py
collabme/validations.py
collabme-0.1.2.dist-info/DESCRIPTION.rst
collabme-0.1.2.dist-info/METADATA
collabme-0.1.2.dist-info/RECORD
collabme-0.1.2.dist-info/WHEEL
collabme-0.1.2.dist-info/metadata.json
collabme-0.1.2.dist-info/top_level.txt
