Metadata-Version: 2.0
Name: collabme
Version: 0.1.2
Summary: collabme client for Python 2.7
Home-page: http://www.secnam.com
Author: Alfred Kars
Author-email: alfred@secnam.com
License: BSD 3-Clause
Keywords: python collaborator kibana mongo api
Platform: UNKNOWN
Classifier: Topic :: Software Development :: Libraries :: Application Frameworks
Classifier: Intended Audience :: Developers
Classifier: Operating System :: POSIX :: Linux
Classifier: Programming Language :: Python
Classifier: Programming Language :: Python :: 2.7
Requires-Dist: requests (==2.18)
